packagehelloworld/__init__.py
packagehelloworld/main.py
packagehelloworld-0.1.5.dist-info/METADATA
packagehelloworld-0.1.5.dist-info/WHEEL
packagehelloworld-0.1.5.dist-info/top_level.txt
packagehelloworld-0.1.5.dist-info/RECORD
