Metadata-Version: 2.4
Name: packagehelloworld
Version: 0.1.5
Summary: A simple hello world Python package.
Requires-Python: >=3.13
